{
  "modelTitle": "CitroenZX",
  "modelPreview": "https://a.d-cd.net/8a8702es-960.jpg",
  "cars": [
    {
      "link": "https://www.drive2.com/r/citroen/zx/1016183/",
      "preview": "https://a.d-cd.net/Y8FCT1DEoATvstClhoGlL_n_cKY-1920.jpg"
    },
    {
      "link": "https://www.drive2.com/r/citroen/zx/530900015179104315/",
      "preview": "https://a.d-cd.net/xaAAAgHiZeA-1920.jpg"
    },
    {
      "link": "https://www.drive2.com/r/citroen/zx/4062246863888330186/",
      "preview": "https://a.d-cd.net/a8ac96u-1920.jpg"
    },
    {
      "link": "https://www.drive2.com/r/citroen/zx/849592/",
      "preview": "https://a.d-cd.net/d0AAAgAD4-A-1920.jpg"
    },
    {
      "link": "https://www.drive2.com/r/citroen/zx/1011378/",
      "preview": "https://a.d-cd.net/2b2168es-1920.jpg"
    },
    {
      "link": "https://www.drive2.com/r/citroen/zx/504737/",
      "preview": "https://a.d-cd.net/5304d58s-1920.jpg"
    },
    {
      "link": "https://www.drive2.com/r/citroen/zx/539630412381554033/",
      "preview": "https://a.d-cd.net/a-AAAgGkvuA-1920.jpg"
    },
    {
      "link": "https://www.drive2.com/r/citroen/zx/1117216/",
      "preview": "https://a.d-cd.net/999093cs-1920.jpg"
    },
    {
      "link": "https://www.drive2.com/r/citroen/zx/593006754107764824/",
      "preview": "https://a.d-cd.net/9DOULWHNtyK6i6eFHFjkJGUVkCQ-1920.jpg"
    },
    {
      "link": "https://www.drive2.com/r/citroen/zx/462211599646590646/",
      "preview": "https://a.d-cd.net/1c547f1s-1920.jpg"
    },
    {
      "link": "https://www.drive2.com/r/citroen/zx/409153/",
      "preview": "https://a.d-cd.net/9ceb0c4s-1920.jpg"
    },
    {
      "link": "https://www.drive2.com/r/citroen/zx/4053239664633453184/",
      "preview": "https://a.d-cd.net/6347eaas-1920.jpg"
    },
    {
      "link": "https://www.drive2.com/r/citroen/zx/1156087/",
      "preview": "https://a.d-cd.net/37ec57cs-1920.jpg"
    },
    {
      "link": "https://www.drive2.com/r/citroen/zx/496733241101779001/",
      "preview": "https://a.d-cd.net/23b422ds-1920.jpg"
    },
    {
      "link": "https://www.drive2.com/r/citroen/zx/547179109462049279/",
      "preview": "https://a.d-cd.net/wWAAAgKGS-A-1920.jpg"
    },
    {
      "link": "https://www.drive2.com/r/citroen/zx/608456541745456662/",
      "preview": "https://a.d-cd.net/KQOcO_7HRb1a7Oyr3mMzYa-vtRE-1920.jpg"
    },
    {
      "link": "https://www.drive2.com/r/citroen/zx/1395098/",
      "preview": "https://a.d-cd.net/6f8fa2as-1920.jpg"
    },
    {
      "link": "https://www.drive2.com/r/citroen/zx/460210488484074285/",
      "preview": "https://a.d-cd.net/1f07ab1s-1920.jpg"
    },
    {
      "link": "https://www.drive2.com/r/citroen/zx/483890670411448869/",
      "preview": "https://a.d-cd.net/2CAAAgGn_eA-1920.jpg"
    },
    {
      "link": "https://www.drive2.com/r/citroen/zx/527050075214449749/",
      "preview": "https://a.d-cd.net/B2AAAgNRluA-1920.jpg"
    },
    {
      "link": "https://www.drive2.com/r/citroen/zx/1535633/",
      "preview": "https://a.d-cd.net/ce42das-1920.jpg"
    },
    {
      "link": "https://www.drive2.com/r/citroen/zx/1215089/",
      "preview": "https://a.d-cd.net/6062dc2s-1920.jpg"
    },
    {
      "link": "https://www.drive2.com/r/citroen/zx/1094234/",
      "preview": "https://a.d-cd.net/355a9aas-1920.jpg"
    },
    {
      "link": "https://www.drive2.com/r/citroen/zx/454430905612632450/",
      "preview": "https://a.d-cd.net/f45fe51s-1920.jpg"
    },
    {
      "link": "https://www.drive2.com/r/citroen/zx/1037753/",
      "preview": "https://a.d-cd.net/54295des-1920.jpg"
    },
    {
      "link": "https://www.drive2.com/r/citroen/zx/460054907588721444/",
      "preview": "https://a.d-cd.net/79465es-1920.jpg"
    },
    {
      "link": "https://www.drive2.com/r/citroen/zx/454234093031261145/",
      "preview": "https://a.d-cd.net/4258c2es-1920.jpg"
    },
    {
      "link": "https://www.drive2.com/r/citroen/zx/490812096108298272/",
      "preview": "https://a.d-cd.net/e220a2ds-1920.jpg"
    },
    {
      "link": "https://www.drive2.com/r/citroen/zx/1257649/",
      "preview": "https://a.d-cd.net/858f7e2s-1920.jpg"
    },
    {
      "link": "https://www.drive2.com/r/citroen/zx/537912975218967276/",
      "preview": "https://a.d-cd.net/3CAAAgIw7uA-1920.jpg"
    },
    {
      "link": "https://www.drive2.com/r/citroen/zx/622097632755473592/",
      "preview": "https://a.d-cd.net/K80sxBMtc9ks06zm2k0KyV11PwE-1920.jpg"
    },
    {
      "link": "https://www.drive2.com/r/citroen/zx/1038658/",
      "preview": "https://a.d-cd.net/dd8a21cs-1920.jpg"
    },
    {
      "link": "https://www.drive2.com/r/citroen/zx/288230376151917381/",
      "preview": "https://a.d-cd.net/8bfd69u-1920.jpg"
    },
    {
      "link": "https://www.drive2.com/r/citroen/zx/560364727780248123/",
      "preview": "https://a.d-cd.net/qmAAAgDgE-A-1920.jpg"
    },
    {
      "link": "https://www.drive2.com/r/citroen/zx/573650126778663117/",
      "preview": "https://a.d-cd.net/lAAAAgDAb-A-1920.jpg"
    },
    {
      "link": "https://www.drive2.com/r/citroen/zx/565462063686615788/",
      "preview": "https://a.d-cd.net/zaAAAgLQN-A-1920.jpg"
    },
    {
      "link": "https://www.drive2.com/r/citroen/zx/924818/",
      "preview": "https://a.d-cd.net/e44f88cs-1920.jpg"
    },
    {
      "link": "https://www.drive2.com/r/citroen/zx/288230376151730971/",
      "preview": "https://a.d-cd.net/a6b3a3u-1920.jpg"
    },
    {
      "link": "https://www.drive2.com/r/citroen/zx/288230376152076627/",
      "preview": "https://a.d-cd.net/ea8ec7u-1920.jpg"
    },
    {
      "link": "https://www.drive2.com/r/citroen/zx/486891787399463828/",
      "preview": "https://a.d-cd.net/QUAAAgHMAOA-1920.jpg"
    },
    {
      "link": "https://www.drive2.com/r/citroen/zx/540596333346555006/",
      "preview": "https://a.d-cd.net/e8AAAgPuVeA-1920.jpg"
    },
    {
      "link": "https://www.drive2.com/r/citroen/zx/593752497869322754/",
      "preview": "https://a.d-cd.net/p5UqYv3BEiNQbIlk2ViadEfW3xE-1920.jpg"
    },
    {
      "link": "https://www.drive2.com/r/citroen/zx/1685939/",
      "preview": "https://a.d-cd.net/3b9b796s-1920.jpg"
    },
    {
      "link": "https://www.drive2.com/r/citroen/zx/530137228987336033/",
      "preview": "https://a.d-cd.net/IsAAAgLONeA-1920.jpg"
    },
    {
      "link": "https://www.drive2.com/r/citroen/zx/584440733893663326/",
      "preview": "https://a.d-cd.net/6zjEq8nw-MFkYrQGzIviXZlg0x8-1920.jpg"
    },
    {
      "link": "https://www.drive2.com/r/citroen/zx/624878847417912429/",
      "preview": "https://a.d-cd.net/vDkxk5k4KrUjNHSO86q4YBQYUpc-1920.jpg"
    },
    {
      "link": "https://www.drive2.com/r/citroen/zx/1143973/",
      "preview": "https://a.d-cd.net/f086bbcs-1920.jpg"
    },
    {
      "link": "https://www.drive2.com/r/citroen/zx/562365838942798482/",
      "preview": "https://a.d-cd.net/noAAAgE3s-A-1920.jpg"
    },
    {
      "link": "https://www.drive2.com/r/citroen/zx/489776081277026847/",
      "preview": "https://a.d-cd.net/101c455s-1920.jpg"
    },
    {
      "link": "https://www.drive2.com/r/citroen/zx/609091234832586815/",
      "preview": "https://a.d-cd.net/WmXMMpV5kGBaEyPxSbhuslxgBbk-1920.jpg"
    },
    {
      "link": "https://www.drive2.com/r/citroen/zx/482329363900006489/",
      "preview": "https://a.d-cd.net/19783b9s-1920.jpg"
    },
    {
      "link": "https://www.drive2.com/r/citroen/zx/480792521522282558/",
      "preview": "https://a.d-cd.net/b4ad6d9s-1920.jpg"
    },
    {
      "link": "https://www.drive2.com/r/citroen/zx/571003052534792214/",
      "preview": "https://a.d-cd.net/ZEAAAgHZN-A-1920.jpg"
    },
    {
      "link": "https://www.drive2.com/r/citroen/zx/594486971636693085/",
      "preview": "https://a.d-cd.net/C0LaYiCwsUMqnrt5ZnDkvYhz5EQ-1920.jpg"
    },
    {
      "link": "https://www.drive2.com/r/citroen/zx/588259612654870122/",
      "preview": "https://a.d-cd.net/7zYY2mQwtlG2sbzVyqrYGTHpcME-1920.jpg"
    },
    {
      "link": "https://www.drive2.com/r/citroen/zx/626412666138676163/",
      "preview": "https://a.d-cd.net/OaczUyoYAiuYBjcCu__p9jYKGpk-1920.jpg"
    },
    {
      "link": "https://www.drive2.com/r/citroen/zx/625699632848065239/",
      "preview": "https://a.d-cd.net/a0YAlQ08oRtA0gqO8KCyFYKlj1k-1920.jpg"
    },
    {
      "link": "https://www.drive2.com/r/citroen/zx/626789523749085828/",
      "preview": "https://a.d-cd.net/G0sBQoiDUmw770ccZxUO28wFt_0-1920.jpg"
    },
    {
      "link": "https://www.drive2.com/r/citroen/zx/1394268/",
      "preview": "https://a.d-cd.net/8a8702es-1920.jpg"
    },
    {
      "link": "https://www.drive2.com/r/citroen/zx/1084856/",
      "preview": "https://a.d-cd.net/1eb6e5cs-1920.jpg"
    },
    {
      "link": "https://www.drive2.com/r/citroen/zx/1093748/",
      "preview": "https://a.d-cd.net/15e675cs-1920.jpg"
    },
    {
      "link": "https://www.drive2.com/r/citroen/zx/614081/",
      "preview": "https://a.d-cd.net/d473g4s-1920.jpg"
    },
    {
      "link": "https://www.drive2.com/r/citroen/zx/665676/",
      "preview": "https://a.d-cd.net/f2dcf24s-1920.jpg"
    },
    {
      "link": "https://www.drive2.com/r/citroen/zx/426118/",
      "preview": "https://a.d-cd.net/bdbffa8s-1920.jpg"
    },
    {
      "link": "https://www.drive2.com/r/citroen/zx/721998/",
      "preview": "https://a.d-cd.net/67a02a4s-1920.jpg"
    },
    {
      "link": "https://www.drive2.com/r/citroen/zx/1426389/",
      "preview": "https://a.d-cd.net/2420daas-1920.jpg"
    },
    {
      "link": "https://www.drive2.com/r/citroen/zx/558811117850199432/",
      "preview": "https://a.d-cd.net/N8AAAgPSg-A-1920.jpg"
    },
    {
      "link": "https://www.drive2.com/r/citroen/zx/1743852/",
      "preview": "https://a.d-cd.net/36fed0es-1920.jpg"
    },
    {
      "link": "https://www.drive2.com/r/citroen/zx/4053239664633480570/",
      "preview": "https://a.d-cd.net/dbcd8eu-1920.jpg"
    },
    {
      "link": "https://www.drive2.com/r/citroen/zx/526809831923779851/",
      "preview": "https://a.d-cd.net/ZCAAAgNZ8uA-1920.jpg"
    },
    {
      "link": "https://www.drive2.com/r/citroen/zx/499046888444526710/",
      "preview": "https://a.d-cd.net/43805eds-1920.jpg"
    },
    {
      "link": "https://www.drive2.com/r/citroen/zx/4062246863888365083/",
      "preview": "https://a.d-cd.net/356ee6u-1920.jpg"
    },
    {
      "link": "https://www.drive2.com/r/citroen/zx/526082504982005480/",
      "preview": "https://a.d-cd.net/sWAAAgKgsuA-1920.jpg"
    },
    {
      "link": "https://www.drive2.com/r/citroen/zx/288230376151991111/",
      "preview": "https://a.d-cd.net/a2f281u-1920.jpg"
    },
    {
      "link": "https://www.drive2.com/r/citroen/zx/562104155175388202/",
      "preview": "https://a.d-cd.net/XWAAAgF_M-A-1920.jpg"
    },
    {
      "link": "https://www.drive2.com/r/citroen/zx/288230376151981874/",
      "preview": "https://a.d-cd.net/7f68c1u-1920.jpg"
    },
    {
      "link": "https://www.drive2.com/r/citroen/zx/586623814230618510/",
      "preview": "https://a.d-cd.net/vE6gWfSXEXrF8PmG06IQ9lvGins-1920.jpg"
    },
    {
      "link": "https://www.drive2.com/r/citroen/zx/1294843/",
      "preview": "https://a.d-cd.net/8c28dd2s-1920.jpg"
    },
    {
      "link": "https://www.drive2.com/r/citroen/zx/719430/",
      "preview": "https://a.d-cd.net/63884a4s-1920.jpg"
    },
    {
      "link": "https://www.drive2.com/r/citroen/zx/1051248/",
      "preview": "https://a.d-cd.net/b9ceb1cs-1920.jpg"
    },
    {
      "link": "https://www.drive2.com/r/citroen/zx/535335719963460395/",
      "preview": "https://a.d-cd.net/HcAAAgGCceA-1920.jpg"
    },
    {
      "link": "https://www.drive2.com/r/citroen/zx/4899916394579133082/",
      "preview": "https://a.d-cd.net/47fc26u-1920.jpg"
    },
    {
      "link": "https://www.drive2.com/r/citroen/zx/593767616154204810/",
      "preview": "https://a.d-cd.net/hDn8Z7hoLH0AXBQxUfW6DAjfNto-1920.jpg"
    },
    {
      "link": "https://www.drive2.com/r/citroen/zx/1041787/",
      "preview": "https://a.d-cd.net/346e61cs-1920.jpg"
    },
    {
      "link": "https://www.drive2.com/r/citroen/zx/534111138888025033/",
      "preview": "https://a.d-cd.net/eQAAAgBu7uA-1920.jpg"
    },
    {
      "link": "https://www.drive2.com/r/citroen/zx/478565735598129385/",
      "preview": "https://a.d-cd.net/c9f2c19s-1920.jpg"
    },
    {
      "link": "https://www.drive2.com/r/citroen/zx/1080282/",
      "preview": "https://a.d-cd.net/99g25cs-1920.jpg"
    },
    {
      "link": "https://www.drive2.com/r/citroen/zx/1328324/",
      "preview": "https://a.d-cd.net/122daas-1920.jpg"
    },
    {
      "link": "https://www.drive2.com/r/citroen/zx/1553237/",
      "preview": "https://a.d-cd.net/650ea3as-1920.jpg"
    },
    {
      "link": "https://www.drive2.com/r/citroen/zx/1381121/",
      "preview": "https://a.d-cd.net/ed67906s-1920.jpg"
    },
    {
      "link": "https://www.drive2.com/r/citroen/zx/461938/",
      "preview": "https://a.d-cd.net/175afe8s-1920.jpg"
    },
    {
      "link": "https://www.drive2.com/r/citroen/zx/415398/",
      "preview": "https://a.d-cd.net/696eea8s-1920.jpg"
    },
    {
      "link": "https://www.drive2.com/r/citroen/zx/610569/",
      "preview": "https://a.d-cd.net/12127f8s-1920.jpg"
    },
    {
      "link": "https://www.drive2.com/r/citroen/zx/712275/",
      "preview": "https://a.d-cd.net/bc0b24s-1920.jpg"
    },
    {
      "link": "https://www.drive2.com/r/citroen/zx/445982/",
      "preview": "https://a.d-cd.net/2c210e8s-1920.jpg"
    },
    {
      "link": "https://www.drive2.com/r/citroen/zx/288230376151867235/",
      "preview": "https://a.d-cd.net/94c6c5u-1920.jpg"
    },
    {
      "link": "https://www.drive2.com/r/citroen/zx/472394451709329927/",
      "preview": "https://a.d-cd.net/75607b1s-1920.jpg"
    },
    {
      "link": "https://www.drive2.com/r/citroen/zx/550230254229128812/",
      "preview": "https://a.d-cd.net/sCAAAgLzReA-1920.jpg"
    },
    {
      "link": "https://www.drive2.com/r/citroen/zx/4899916394579102255/",
      "preview": "https://a.d-cd.net/9c2a66u-1920.jpg"
    },
    {
      "link": "https://www.drive2.com/r/citroen/zx/1071757/",
      "preview": "https://a.d-cd.net/f384b9cs-1920.jpg"
    },
    {
      "link": "https://www.drive2.com/r/citroen/zx/624839/",
      "preview": "https://a.d-cd.net/9982904s-1920.jpg"
    },
    {
      "link": "https://www.drive2.com/r/citroen/zx/417171/",
      "preview": "https://a.d-cd.net/11471a8s-1920.jpg"
    },
    {
      "link": "https://www.drive2.com/r/citroen/zx/463188/",
      "preview": "https://a.d-cd.net/17f38s-1920.jpg"
    },
    {
      "link": "https://www.drive2.com/r/citroen/zx/308862/",
      "preview": "https://a.d-cd.net/121c9c8s-1920.jpg"
    },
    {
      "link": "https://www.drive2.com/r/citroen/zx/416585/",
      "preview": "https://a.d-cd.net/de0e1a8s-1920.jpg"
    },
    {
      "link": "https://www.drive2.com/r/citroen/zx/614128097599436220/",
      "preview": "https://a.d-cd.net/OFQcooV10i1lmqEp5RThl8JJlsI-1920.jpg"
    },
    {
      "link": "https://www.drive2.com/r/citroen/zx/692319/",
      "preview": "https://a.d-cd.net/fbf7bc4s-1920.jpg"
    },
    {
      "link": "https://www.drive2.com/r/citroen/zx/479971186336333895/",
      "preview": "https://a.d-cd.net/34a0839s-1920.jpg"
    },
    {
      "link": "https://www.drive2.com/r/citroen/zx/906549/",
      "preview": "https://a.d-cd.net/da7cdf4s-1920.jpg"
    },
    {
      "link": "https://www.drive2.com/r/citroen/zx/444198/",
      "preview": "https://a.d-cd.net/dc57984s-1920.jpg"
    },
    {
      "link": "https://www.drive2.com/r/citroen/zx/952064/",
      "preview": "https://a.d-cd.net/68364ccs-1920.jpg"
    },
    {
      "link": "https://www.drive2.com/r/citroen/zx/1666792/",
      "preview": "https://a.d-cd.net/62ee1e6s-1920.jpg"
    },
    {
      "link": "https://www.drive2.com/r/citroen/zx/545944907659871010/",
      "preview": "https://a.d-cd.net/nxAAAgFGb-A-1920.jpg"
    },
    {
      "link": "https://www.drive2.com/r/citroen/zx/608772101582630724/",
      "preview": "https://a.d-cd.net/lcC39nCSW9LoF7ZmfyCv3CyQB-k-1920.jpg"
    },
    {
      "link": "https://www.drive2.com/r/citroen/zx/288230376151928641/",
      "preview": "https://a.d-cd.net/f25fed5s-1920.jpg"
    },
    {
      "link": "https://www.drive2.com/r/citroen/zx/1119910/",
      "preview": "https://a.d-cd.net/4d6663cs-1920.jpg"
    },
    {
      "link": "https://www.drive2.com/r/citroen/zx/457784416077376686/",
      "preview": "https://a.d-cd.net/656a01es-1920.jpg"
    },
    {
      "link": "https://www.drive2.com/r/citroen/zx/1176162/",
      "preview": "https://a.d-cd.net/2e9c802s-1920.jpg"
    },
    {
      "link": "https://www.drive2.com/r/citroen/zx/557507646815470092/",
      "preview": "https://a.d-cd.net/-gAAAgJVPeA-1920.jpg"
    },
    {
      "link": "https://www.drive2.com/r/citroen/zx/409859/",
      "preview": "https://a.d-cd.net/8968ca8s-1920.jpg"
    },
    {
      "link": "https://www.drive2.com/r/citroen/zx/1199114/",
      "preview": "https://a.d-cd.net/9f91442s-1920.jpg"
    },
    {
      "link": "https://www.drive2.com/r/citroen/zx/1308290/",
      "preview": "https://a.d-cd.net/d6404b2s-1920.jpg"
    },
    {
      "link": "https://www.drive2.com/r/citroen/zx/288230376152047783/",
      "preview": "https://a.d-cd.net/23315eu-1920.jpg"
    },
    {
      "link": "https://www.drive2.com/r/citroen/zx/1537797/",
      "preview": "https://a.d-cd.net/8a8702es-1920.jpg"
    },
    {
      "link": "https://www.drive2.com/r/citroen/zx/748125/",
      "preview": "https://a.d-cd.net/bd3da64s-1920.jpg"
    },
    {
      "link": "https://www.drive2.com/r/citroen/zx/1729382256910327094/",
      "preview": "https://a.d-cd.net/32baeu-1920.jpg"
    },
    {
      "link": "https://www.drive2.com/r/citroen/zx/564646775814619589/",
      "preview": "https://a.d-cd.net/1wAAAgPYa-A-1920.jpg"
    },
    {
      "link": "https://www.drive2.com/r/citroen/zx/491442666026828171/",
      "preview": "https://a.d-cd.net/c446335s-1920.jpg"
    },
    {
      "link": "https://www.drive2.com/r/citroen/zx/446036/",
      "preview": "https://a.d-cd.net/f3890e8s-1920.jpg"
    },
    {
      "link": "https://www.drive2.com/r/citroen/zx/495596620956566276/",
      "preview": "https://a.d-cd.net/296e54ds-1920.jpg"
    },
    {
      "link": "https://www.drive2.com/r/citroen/zx/547106541694615762/",
      "preview": "https://a.d-cd.net/uQAAAgFt6eA-1920.jpg"
    },
    {
      "link": "https://www.drive2.com/r/citroen/zx/457694531001785404/",
      "preview": "https://a.d-cd.net/4b567ees-1920.jpg"
    },
    {
      "link": "https://www.drive2.com/r/citroen/zx/460170081431740209/",
      "preview": "https://a.d-cd.net/499195es-1920.jpg"
    },
    {
      "link": "https://www.drive2.com/r/citroen/zx/1045397/",
      "preview": "https://a.d-cd.net/17780b2s-1920.jpg"
    },
    {
      "link": "https://www.drive2.com/r/citroen/zx/905513/",
      "preview": "https://a.d-cd.net/5e205f4s-1920.jpg"
    },
    {
      "link": "https://www.drive2.com/r/citroen/zx/579784851905839269/",
      "preview": "https://a.d-cd.net/HfbS26E-R9tO3u_Gkr8GRXxAbuI-1920.jpg"
    },
    {
      "link": "https://www.drive2.com/r/citroen/zx/576134748179530276/",
      "preview": "https://a.d-cd.net/W_fAtOIKABKjn6S9otYBfZMrpRA-1920.jpg"
    },
    {
      "link": "https://www.drive2.com/r/citroen/zx/546028/",
      "preview": "https://a.d-cd.net/1fddfdcs-1920.jpg"
    },
    {
      "link": "https://www.drive2.com/r/citroen/zx/533935217027580493/",
      "preview": "https://a.d-cd.net/vgAAAgJXFuA-1920.jpg"
    },
    {
      "link": "https://www.drive2.com/r/citroen/zx/1747396655419763650/",
      "preview": "https://a.d-cd.net/f784aeu-1920.jpg"
    },
    {
      "link": "https://www.drive2.com/r/citroen/zx/455113/",
      "preview": "https://a.d-cd.net/7b522b2s-1920.jpg"
    },
    {
      "link": "https://www.drive2.com/r/citroen/zx/459940283501552066/",
      "preview": "https://a.d-cd.net/e60265es-1920.jpg"
    },
    {
      "link": "https://www.drive2.com/r/citroen/zx/545502903985504302/",
      "preview": "https://a.d-cd.net/0gAAAgAgSeA-1920.jpg"
    },
    {
      "link": "https://www.drive2.com/r/citroen/zx/1479346/",
      "preview": "https://a.d-cd.net/8a8702es-1920.jpg"
    },
    {
      "link": "https://www.drive2.com/r/citroen/zx/1096821/",
      "preview": "https://a.d-cd.net/e58b0dcs-1920.jpg"
    },
    {
      "link": "https://www.drive2.com/r/citroen/zx/1157616/",
      "preview": "https://a.d-cd.net/c267d7cs-1920.jpg"
    },
    {
      "link": "https://www.drive2.com/r/citroen/zx/454595282600986813/",
      "preview": "https://a.d-cd.net/59fd12es-1920.jpg"
    },
    {
      "link": "https://www.drive2.com/r/citroen/zx/471084933360648961/",
      "preview": "https://a.d-cd.net/20e0c71s-1920.jpg"
    },
    {
      "link": "https://www.drive2.com/r/citroen/zx/484308759707910540/",
      "preview": "https://a.d-cd.net/e702305s-1920.jpg"
    },
    {
      "link": "https://www.drive2.com/r/citroen/zx/288230376151819826/",
      "preview": "https://a.d-cd.net/45730du-1920.jpg"
    },
    {
      "link": "https://www.drive2.com/r/citroen/zx/1201016/",
      "preview": "https://a.d-cd.net/2856a42s-1920.jpg"
    },
    {
      "link": "https://www.drive2.com/r/citroen/zx/1538377/",
      "preview": "https://a.d-cd.net/8a8702es-1920.jpg"
    },
    {
      "link": "https://www.drive2.com/r/citroen/zx/288230376151992049/",
      "preview": "https://a.d-cd.net/82f481u-1920.jpg"
    },
    {
      "link": "https://www.drive2.com/r/citroen/zx/545207685113446577/",
      "preview": "https://a.d-cd.net/IwAAAgLvCeA-1920.jpg"
    },
    {
      "link": "https://www.drive2.com/r/citroen/zx/555242377984344995/",
      "preview": "https://a.d-cd.net/ykAAAgB5LeA-1920.jpg"
    },
    {
      "link": "https://www.drive2.com/r/citroen/zx/376491/",
      "preview": "https://a.d-cd.net/d04bc28s-1920.jpg"
    },
    {
      "link": "https://www.drive2.com/r/citroen/zx/4062246863888394478/",
      "preview": "https://a.d-cd.net/1ccedv/480.jpg"
    },
    {
      "link": "https://www.drive2.com/r/citroen/zx/489215605224767632/",
      "preview": "https://a.d-cd.net/6be5895s-1920.jpg"
    },
    {
      "link": "https://www.drive2.com/r/citroen/zx/556510/",
      "preview": "https://a.d-cd.net/c0292b8s-1920.jpg"
    },
    {
      "link": "https://www.drive2.com/r/citroen/zx/1377594/",
      "preview": "https://a.d-cd.net/8a8702es-1920.jpg"
    },
    {
      "link": "https://www.drive2.com/r/citroen/zx/4062246863888190640/",
      "preview": "https://a.d-cd.net/22e48eu-1920.jpg"
    },
    {
      "link": "https://www.drive2.com/r/citroen/zx/1688433/",
      "preview": "https://a.d-cd.net/cd74256s-1920.jpg"
    },
    {
      "link": "https://www.drive2.com/r/citroen/zx/508300378303890390/",
      "preview": "https://a.d-cd.net/bYAAAgAbsOA-1920.jpg"
    },
    {
      "link": "https://www.drive2.com/r/citroen/zx/462055743873351851/",
      "preview": "https://a.d-cd.net/692263es-1920.jpg"
    },
    {
      "link": "https://www.drive2.com/r/citroen/zx/516573928424997568/",
      "preview": "https://a.d-cd.net/eYAAAgC81OA-1920.jpg"
    }
  ]
}