{
  "modelTitle": "CadillacDeVille(8G)",
  "modelPreview": "https://a.d-cd.net/90a4fces-960.jpg",
  "cars": [
    {
      "link": "https://www.drive2.com/r/cadillac/de_ville/1220585/",
      "preview": "https://a.d-cd.net/c2aac22s-1920.jpg"
    },
    {
      "link": "https://www.drive2.com/r/cadillac/de_ville/1302404/",
      "preview": "https://a.d-cd.net/319de32s-1920.jpg"
    },
    {
      "link": "https://www.drive2.com/r/cadillac/de_ville/379376/",
      "preview": "https://a.d-cd.net/280ce28s-1920.jpg"
    },
    {
      "link": "https://www.drive2.com/r/cadillac/de_ville/1529166/",
      "preview": "https://a.d-cd.net/c22d75as-1920.jpg"
    },
    {
      "link": "https://www.drive2.com/r/cadillac/de_ville/545261286305302517/",
      "preview": "https://a.d-cd.net/xCAAAgPkieA-1920.jpg"
    },
    {
      "link": "https://www.drive2.com/r/cadillac/de_ville/570898324052247415/",
      "preview": "https://a.d-cd.net/k-AAAgC8N-A-1920.jpg"
    },
    {
      "link": "https://www.drive2.com/r/cadillac/de_ville/458492776443609047/",
      "preview": "https://a.d-cd.net/c0f231es-1920.jpg"
    },
    {
      "link": "https://www.drive2.com/r/cadillac/de_ville/622828/",
      "preview": "https://a.d-cd.net/5b85e04s-1920.jpg"
    },
    {
      "link": "https://www.drive2.com/r/cadillac/de_ville/998902/",
      "preview": "https://a.d-cd.net/cf735dcs-1920.jpg"
    },
    {
      "link": "https://www.drive2.com/r/cadillac/de_ville/500001539415343171/",
      "preview": "https://a.d-cd.net/a9689ds-1920.jpg"
    },
    {
      "link": "https://www.drive2.com/r/cadillac/de_ville/288230376152080866/",
      "preview": "https://a.d-cd.net/895148s-1920.jpg"
    },
    {
      "link": "https://www.drive2.com/r/cadillac/de_ville/460241824565457007/",
      "preview": "https://a.d-cd.net/f704371s-1920.jpg"
    },
    {
      "link": "https://www.drive2.com/r/cadillac/de_ville/4035225266124036237/",
      "preview": "https://a.d-cd.net/7b31ceu-1920.jpg"
    },
    {
      "link": "https://www.drive2.com/r/cadillac/de_ville/855534/",
      "preview": "https://a.d-cd.net/8541bd4s-1920.jpg"
    },
    {
      "link": "https://www.drive2.com/r/cadillac/de_ville/1729382256910310420/",
      "preview": "https://a.d-cd.net/a7926eu-1920.jpg"
    },
    {
      "link": "https://www.drive2.com/r/cadillac/de_ville/480332101028151745/",
      "preview": "https://a.d-cd.net/5dd4359s-1920.jpg"
    },
    {
      "link": "https://www.drive2.com/r/cadillac/de_ville/288230376152037066/",
      "preview": "https://a.d-cd.net/a49ddeu-1920.jpg"
    },
    {
      "link": "https://www.drive2.com/r/cadillac/de_ville/288230376151814066/",
      "preview": "https://a.d-cd.net/5c10cdu-1920.jpg"
    },
    {
      "link": "https://www.drive2.com/r/cadillac/de_ville/493120245892907058/",
      "preview": "https://a.d-cd.net/ca4c0f5s-1920.jpg"
    },
    {
      "link": "https://www.drive2.com/r/cadillac/de_ville/852855/",
      "preview": "https://a.d-cd.net/81ae7d4s-1920.jpg"
    },
    {
      "link": "https://www.drive2.com/r/cadillac/de_ville/695344/",
      "preview": "https://a.d-cd.net/69d31a4s-1920.jpg"
    }
  ]
}