{
  "modelTitle": "MitsubishiToppoII",
  "modelPreview": "https://a.d-cd.net/d07092es-960.jpg",
  "cars": [
    {
      "link": "https://www.drive2.com/r/mitsubishi/toppo/1431631/",
      "preview": "https://a.d-cd.net/d742585s-1920.jpg"
    },
    {
      "link": "https://www.drive2.com/r/mitsubishi/toppo/911978/",
      "preview": "https://a.d-cd.net/97cf80cs-1920.jpg"
    },
    {
      "link": "https://www.drive2.com/r/mitsubishi/toppo/1512679/",
      "preview": "https://a.d-cd.net/67e085as-1920.jpg"
    },
    {
      "link": "https://www.drive2.com/r/mitsubishi/toppo/531706506958078256/",
      "preview": "https://a.d-cd.net/9KAAAgAAhuA-1920.jpg"
    },
    {
      "link": "https://www.drive2.com/r/mitsubishi/toppo/505761056199540782/",
      "preview": "https://a.d-cd.net/JYAAAgLnNOA-1920.jpg"
    }
  ]
}