{
  "modelTitle": "ToyotaAvalon(2G)",
  "modelPreview": "https://a.d-cd.net/ukAAAgNz7uA-960.jpg",
  "cars": [
    {
      "link": "https://www.drive2.com/r/toyota/avalon/481103683312943529/",
      "preview": "https://a.d-cd.net/f7c3fc5s-1920.jpg"
    },
    {
      "link": "https://www.drive2.com/r/toyota/avalon/912283/",
      "preview": "https://a.d-cd.net/acbc621s-1920.jpg"
    },
    {
      "link": "https://www.drive2.com/r/toyota/avalon/579461045731459754/",
      "preview": "https://a.d-cd.net/vG__4DfVb2PpVj83LzYwkqlKVOc-1920.jpg"
    },
    {
      "link": "https://www.drive2.com/r/toyota/avalon/4062246863888364109/",
      "preview": "https://a.d-cd.net/2661e6u-1920.jpg"
    },
    {
      "link": "https://www.drive2.com/r/toyota/avalon/865347/",
      "preview": "https://a.d-cd.net/6e07134s-1920.jpg"
    },
    {
      "link": "https://www.drive2.com/r/toyota/avalon/4899916394579115384/",
      "preview": "https://a.d-cd.net/3072a6u-1920.jpg"
    },
    {
      "link": "https://www.drive2.com/r/toyota/avalon/452326715234980136/",
      "preview": "https://a.d-cd.net/2b7fc4es-1920.jpg"
    },
    {
      "link": "https://www.drive2.com/r/toyota/avalon/458416635263406914/",
      "preview": "https://a.d-cd.net/e7b0d1es-1920.jpg"
    },
    {
      "link": "https://www.drive2.com/r/toyota/avalon/485775783097270345/",
      "preview": "https://a.d-cd.net/46534c5s-1920.jpg"
    },
    {
      "link": "https://www.drive2.com/r/toyota/avalon/1081317/",
      "preview": "https://a.d-cd.net/bb4325cs-1920.jpg"
    },
    {
      "link": "https://www.drive2.com/r/toyota/avalon/1489612/",
      "preview": "https://a.d-cd.net/c2e41fas-1920.jpg"
    },
    {
      "link": "https://www.drive2.com/r/toyota/avalon/583237043539205996/",
      "preview": "https://a.d-cd.net/Ne8fApJrcMp3Dq0Ec5agyVFVZWs-1920.jpg"
    },
    {
      "link": "https://www.drive2.com/r/toyota/avalon/686422/",
      "preview": "https://a.d-cd.net/a579134s-1920.jpg"
    },
    {
      "link": "https://www.drive2.com/r/toyota/avalon/455619752560167545/",
      "preview": "https://a.d-cd.net/82bf9aes-1920.jpg"
    },
    {
      "link": "https://www.drive2.com/r/toyota/avalon/624896439603955945/",
      "preview": "https://a.d-cd.net/ew5CV8zH_B4NjoLCu5OCoNRVnMo-1920.jpg"
    },
    {
      "link": "https://www.drive2.com/r/toyota/avalon/436891/",
      "preview": "https://a.d-cd.net/25b0968s-1920.jpg"
    },
    {
      "link": "https://www.drive2.com/r/toyota/avalon/101653/",
      "preview": "https://a.d-cd.net/72320au-1920.jpg"
    },
    {
      "link": "https://www.drive2.com/r/toyota/avalon/480155904289800668/",
      "preview": "https://a.d-cd.net/8d66f59s-1920.jpg"
    },
    {
      "link": "https://www.drive2.com/r/toyota/avalon/566241892308615463/",
      "preview": "https://a.d-cd.net/QCAAAgGN2-A-1920.jpg"
    },
    {
      "link": "https://www.drive2.com/r/toyota/avalon/512315/",
      "preview": "https://a.d-cd.net/31e88d8s-1920.jpg"
    }
  ]
}