{
  "modelTitle": "Peugeot407SW",
  "modelPreview": "https://a.d-cd.net/556852es-960.jpg",
  "cars": [
    {
      "link": "https://www.drive2.com/r/peugeot/407_sw/539326947172287280/",
      "preview": "https://a.d-cd.net/iRAAAgPJceA-1920.jpg"
    },
    {
      "link": "https://www.drive2.com/r/peugeot/407_sw/537920396922454076/",
      "preview": "https://a.d-cd.net/8QAAAgHI7uA-1920.jpg"
    },
    {
      "link": "https://www.drive2.com/r/peugeot/407_sw/451131271217676622/",
      "preview": "https://a.d-cd.net/IiAAAgJMfuA-1920.jpg"
    },
    {
      "link": "https://www.drive2.com/r/peugeot/407_sw/478702075039973431/",
      "preview": "https://a.d-cd.net/f1c3ca5s-1920.jpg"
    },
    {
      "link": "https://www.drive2.com/r/peugeot/407_sw/1235440/",
      "preview": "https://a.d-cd.net/6171962s-1920.jpg"
    },
    {
      "link": "https://www.drive2.com/r/peugeot/407_sw/592760738381057489/",
      "preview": "https://a.d-cd.net/QALvdzAOHIlcZ6BA2bZI4AdZX1s-1920.jpg"
    },
    {
      "link": "https://www.drive2.com/r/peugeot/407_sw/520963453720986340/",
      "preview": "https://a.d-cd.net/VZoDwZ6onICJKAAxNX7NI9rL8fQ-1920.jpg"
    },
    {
      "link": "https://www.drive2.com/r/peugeot/407_sw/492936352573162324/",
      "preview": "https://a.d-cd.net/f0b4375s-1920.jpg"
    },
    {
      "link": "https://www.drive2.com/r/peugeot/407_sw/840179/",
      "preview": "https://a.d-cd.net/666f8c9s-1920.jpg"
    },
    {
      "link": "https://www.drive2.com/r/peugeot/407_sw/577822773406072940/",
      "preview": "https://a.d-cd.net/ZKC9UQF0jgEBALDVsXxfFpBB5yo-1920.jpg"
    },
    {
      "link": "https://www.drive2.com/r/peugeot/407_sw/508708297117794346/",
      "preview": "https://a.d-cd.net/BGAAAgEdRuA-1920.jpg"
    },
    {
      "link": "https://www.drive2.com/r/peugeot/407_sw/546275585781925650/",
      "preview": "https://a.d-cd.net/0wAAAgPgC-A-1920.jpg"
    },
    {
      "link": "https://www.drive2.com/r/peugeot/407_sw/1554030/",
      "preview": "https://a.d-cd.net/f363a2es-1920.jpg"
    },
    {
      "link": "https://www.drive2.com/r/peugeot/407_sw/845039/",
      "preview": "https://a.d-cd.net/2a26dacs-1920.jpg"
    },
    {
      "link": "https://www.drive2.com/r/peugeot/407_sw/611205870570730692/",
      "preview": "https://a.d-cd.net/j1vrcsWIXXE1WaH6FC1VJvNys58-1920.jpg"
    },
    {
      "link": "https://www.drive2.com/r/peugeot/407_sw/541863795375473356/",
      "preview": "https://a.d-cd.net/dwAAAgCMkeA-1920.jpg"
    },
    {
      "link": "https://www.drive2.com/r/peugeot/407_sw/1161389/",
      "preview": "https://a.d-cd.net/c1d40fcs-1920.jpg"
    },
    {
      "link": "https://www.drive2.com/r/peugeot/407_sw/1698396/",
      "preview": "https://a.d-cd.net/afcbbc5s-1920.jpg"
    },
    {
      "link": "https://www.drive2.com/r/peugeot/407_sw/478144072888877570/",
      "preview": "https://a.d-cd.net/oHsGuGBQv12zqi96ASXpwCGuQfg-1920.jpg"
    },
    {
      "link": "https://www.drive2.com/r/peugeot/407_sw/1318389/",
      "preview": "https://a.d-cd.net/7292856s-1920.jpg"
    }
  ]
}