{
  "modelTitle": "PlymouthGranFury",
  "modelPreview": "https://a.d-cd.net/b11dd2es-960.jpg",
  "cars": [
    {
      "link": "https://www.drive2.com/r/plymouth/gran_fury/314313/",
      "preview": "https://a.d-cd.net/cf06945s-1920.jpg"
    },
    {
      "link": "https://www.drive2.com/r/plymouth/gran_fury/1094562/",
      "preview": "https://a.d-cd.net/c6c0f5cs-1920.jpg"
    },
    {
      "link": "https://www.drive2.com/r/plymouth/gran_fury/1523221/",
      "preview": "https://a.d-cd.net/e57d95as-1920.jpg"
    }
  ]
}